docmesh_cli/__init__.py
docmesh_cli/client.py
docmesh_cli/logos.py
docmesh_cli-0.0.12.dist-info/entry_points.txt
docmesh_cli-0.0.12.dist-info/WHEEL
docmesh_cli-0.0.12.dist-info/METADATA
docmesh_cli-0.0.12.dist-info/RECORD
