Metadata-Version: 2.1
Name: docmesh_cli
Version: 0.0.12
Summary: Client for docmesh.
Author-email: Zhengkai Yang <kyle.yang1995@gmail.com>
Requires-Python: >=3.8
Classifier: Programming Language :: Python :: 3.8
Classifier: Programming Language :: Python :: 3.9
Classifier: Programming Language :: Python :: 3.10
Classifier: Operating System :: OS Independent
Requires-Dist: requests>=2.31.0
Requires-Dist: packaging>=23.2
